setup.py
booley/__init__.py
booley/exceptions.py
booley/parsers.py
booley/tests.py
booley/utils.py
booley.egg-info/PKG-INFO
booley.egg-info/SOURCES.txt
booley.egg-info/dependency_links.txt
booley.egg-info/requires.txt
booley.egg-info/top_level.txt