Metadata-Version: 1.0
Name: booley
Version: 0.1.1
Summary: A meta-language to evaluate boolean expressions using a dict keys as context variables.
Home-page: https://github.com/kasappeal/booley
Author: Alberto Casero
Author-email: kas.appeal@gmail.com
License: MIT
Platform: UNKNOWN
